mathify/__init__.py
mathify/algebra.py
mathify/arithmetic.py
mathify_ramc-0.3.0.dist-info/licenses/license
mathify_ramc-0.3.0.dist-info/METADATA
mathify_ramc-0.3.0.dist-info/WHEEL
mathify_ramc-0.3.0.dist-info/entry_points.txt
mathify_ramc-0.3.0.dist-info/top_level.txt
mathify_ramc-0.3.0.dist-info/RECORD
